flask_kit/__init__.py
flask_kit/api.py
flask_kit/database.py
flask_kit/migrate.py
flask_kit/sources.py
flask_kit-0.0.1.dist-info/DESCRIPTION.rst
flask_kit-0.0.1.dist-info/METADATA
flask_kit-0.0.1.dist-info/RECORD
flask_kit-0.0.1.dist-info/WHEEL
flask_kit-0.0.1.dist-info/metadata.json
flask_kit-0.0.1.dist-info/top_level.txt
