Metadata-Version: 2.0
Name: flask-kit
Version: 0.0.1
Summary: Flask extension pack for quick start
Home-page: https://bitbucket.org/rysev-a/flask-kit
Author: Rysev Alexei
Author-email: alexeirysev@gmail.com
License: UNKNOWN
Platform: UNKNOWN
Classifier: Programming Language :: Python :: 3.6
Classifier: License :: OSI Approved :: MIT License
Classifier: Operating System :: OS Independent
Requires-Dist: Flask (==1.0.2)
Requires-Dist: Flask-Migrate (==2.3.0)
Requires-Dist: Flask-RESTful (==0.3.6)
Requires-Dist: Flask-SQLAlchemy (==2.3.2)
Requires-Dist: SQLAlchemy (==1.2.9)
